geompy/__init__.py
geompy/line/__init__.py
geompy/line/check_intersect.py
geompy/line/intersect_point.py
geompy/plane/__init__.py
geompy/plane/check_parallel.py
geompy/point/__init__.py
geompy/point/on_line.py
geompy/point/on_plane.py
geompy-0.0.1.dist-info/LICENSE
geompy-0.0.1.dist-info/METADATA
geompy-0.0.1.dist-info/WHEEL
geompy-0.0.1.dist-info/top_level.txt
geompy-0.0.1.dist-info/RECORD
