Metadata-Version: 2.1
Name: geompy
Version: 0.0.1
Summary: A Python package for practical geometry algorithms.
Home-page: https://github.com/mctrinh/geompy
Author: Minh-Chien Trinh
Author-email: Minh-Chien Trinh <mctrinh@jbnu.ac.kr>
License: MIT
Project-URL: Homepage, https://github.com/mctrinh/geompy
Project-URL: Bug Tracker, https://github.com/mctrinh/geompy/issues
Keywords: geometry,geompy
Classifier: Programming Language :: Python :: 3
Classifier: License :: OSI Approved :: MIT License
Classifier: Operating System :: OS Independent
Requires-Python: >=3.7
License-File: LICENSE
